flash/__init__.py
flash/api.py
flash/constants.py
flash/error_handlers.py
flash/exceptions.py
flash/middleware.py
flash/orm.py
flash/requests.py
flash/responses.py
flash/route.py
flash/templates.py
flash/util/__init__.py
flash/util/static.py
flash/util/tests.py
flash/util/wsgi.py
flash_framework-1.0.0.dist-info/METADATA
flash_framework-1.0.0.dist-info/WHEEL
flash_framework-1.0.0.dist-info/top_level.txt
flash_framework-1.0.0.dist-info/RECORD
