Metadata-Version: 2.1
Name: flash-framework
Version: 1.0.0
Summary: Python Web Framework built for learning and fun.
Home-page: https://github.com/devil-cyber/flash
Author: Manikant Kumar
Author-email: mani2474695@gmail.com
License: MIT
Platform: UNKNOWN
Classifier: License :: OSI Approved :: MIT License
Classifier: Programming Language :: Python
Classifier: Programming Language :: Python :: 3
Classifier: Programming Language :: Python :: 3.8
Classifier: Programming Language :: Python :: Implementation :: CPython
Classifier: Programming Language :: Python :: Implementation :: PyPy
Requires-Python: >=3.6.9
Requires-Dist: attrs (==21.2.0)
Requires-Dist: charset-normalizer (==2.0.1)
Requires-Dist: gunicorn (==20.1.0)
Requires-Dist: idna (==3.2)
Requires-Dist: iniconfig (==1.1.1)
Requires-Dist: Jinja2 (==3.0.1)
Requires-Dist: MarkupSafe (==2.0.1)
Requires-Dist: packaging (==21.0)
Requires-Dist: parse (==1.19.0)
Requires-Dist: pluggy (==0.13.1)
Requires-Dist: py (==1.10.0)
Requires-Dist: pyparsing (==2.4.7)
Requires-Dist: pytest (==6.2.4)
Requires-Dist: requests (==2.26.0)
Requires-Dist: requests-wsgi-adapter (==0.4.1)
Requires-Dist: toml (==0.10.2)
Requires-Dist: urllib3 (==1.26.6)
Requires-Dist: WebOb (==1.8.7)
Requires-Dist: whitenoise (==5.2.0)
